distributex/__init__.py
distributex_cloud-8.0.6.dist-info/METADATA
distributex_cloud-8.0.6.dist-info/WHEEL
distributex_cloud-8.0.6.dist-info/top_level.txt
distributex_cloud-8.0.6.dist-info/RECORD
