Metadata-Version: 2.4
Name: distributex-cloud
Version: 8.0.6
Summary: Python SDK for DistributeX distributed computing
Home-page: https://github.com/DistributeX-Cloud/distributex
Author: DistributeX Team
Author-email: DistributeX <support@distributex.cloud>
License: MIT
Project-URL: Homepage, https://distributex.cloud
Project-URL: Documentation, https://docs.distributex.cloud
Project-URL: Repository, https://github.com/DistributeX-Cloud/distributex
Project-URL: Changelog, https://github.com/DistributeX-Cloud/distributex/blob/main/CHANGELOG.md
Keywords: distributed,computing,cloud,serverless
Classifier: Development Status :: 4 - Beta
Classifier: Intended Audience :: Developers
Classifier: License :: OSI Approved :: MIT License
Classifier: Programming Language :: Python :: 3
Classifier: Programming Language :: Python :: 3.8
Classifier: Programming Language :: Python :: 3.9
Classifier: Programming Language :: Python :: 3.10
Classifier: Programming Language :: Python :: 3.11
Requires-Python: >=3.8
Requires-Dist: requests>=2.31.0
Dynamic: author
Dynamic: home-page
Dynamic: requires-python
